{"version":"3.16.1","flags":{"man":false,"left_eye_open":false,"right_eye_open":false,"mouth_open_large":false,"mouth_open_small":false,"glasses":false,"infrared_glasses":false,"left_phone":false,"right_phone":false,"smoke":false,"drink":false,"mask":false,"lateral_face":false,"positive_face":false,"incomplete_display":false,"underexposure":false},"shapes":[{"label":"face_box","points":[[443,164],[672,471]],"shape_type":"rectangle"},{"label":"left_eyebrow","points":[[488,250],[522,240],[557,243]],"shape_type":"linestrip"},{"label":"right_eyebrow","points":[[615,247],[637,245],[656,252]],"shape_type":"linestrip"},{"label":"left_eye","points":[[508,280],[530,269],[551,282],[530,285],[533,278]],"shape_type":"linestrip"},{"label":"right_eye","points":[[616,285],[636,274],[652,286],[636,290],[634,282]],"shape_type":"linestrip"},{"label":"nose","points":[[603,325],[563,343],[622,344]],"shape_type":"linestrip"},{"label":"mouth","points":[[555,394],[600,374],[599,385],[626,394],[600,406],[599,392]],"shape_type":"linestrip"}],"lineColor":[0,255,0,128],"fillColor":[255,0,0,128],"imagePath":"/storage/sdcard1/sample2w8/DMS_Video_and_Image_200w_image_shake_1_20001-28460/Shake_1_1190619_1min_488.jpg","imageHeight":720,"imageWidth":1280}